LICENSE
README.md
setup.py
kafi/__init__.py
kafi/addons.py
kafi/deserializer.py
kafi/files.py
kafi/functional.py
kafi/helpers.py
kafi/kafi.py
kafi/pandas.py
kafi/schemaregistry.py
kafi/serializer.py
kafi/shell.py
kafi/storage.py
kafi/storage_admin.py
kafi/storage_consumer.py
kafi/storage_producer.py
kafi.egg-info/PKG-INFO
kafi.egg-info/SOURCES.txt
kafi.egg-info/dependency_links.txt
kafi.egg-info/requires.txt
kafi.egg-info/top_level.txt
kafi/fs/__init__.py
kafi/fs/fs.py
kafi/fs/fs_admin.py
kafi/fs/fs_consumer.py
kafi/fs/fs_producer.py
kafi/fs/azureblob/__init__.py
kafi/fs/azureblob/azureblob.py
kafi/fs/azureblob/azureblob_admin.py
kafi/fs/azureblob/azureblob_consumer.py
kafi/fs/azureblob/azureblob_producer.py
kafi/fs/local/__init__.py
kafi/fs/local/local.py
kafi/fs/local/local_admin.py
kafi/fs/local/local_consumer.py
kafi/fs/local/local_producer.py
kafi/fs/s3/__init__.py
kafi/fs/s3/s3.py
kafi/fs/s3/s3_admin.py
kafi/fs/s3/s3_consumer.py
kafi/fs/s3/s3_producer.py
kafi/kafka/__init__.py
kafi/kafka/kafka.py
kafi/kafka/kafka_admin.py
kafi/kafka/kafka_consumer.py
kafi/kafka/kafka_producer.py
kafi/kafka/cluster/__init__.py
kafi/kafka/cluster/cluster.py
kafi/kafka/cluster/cluster_admin.py
kafi/kafka/cluster/cluster_consumer.py
kafi/kafka/cluster/cluster_producer.py
kafi/kafka/restproxy/__init__.py
kafi/kafka/restproxy/restproxy.py
kafi/kafka/restproxy/restproxy_admin.py
kafi/kafka/restproxy/restproxy_consumer.py
kafi/kafka/restproxy/restproxy_producer.py
test/__init__.py
test/test_cross_storage.py
test/test_fs_azureblob.py
test/test_fs_local.py
test/test_fs_s3.py
test/test_kafka_cluster.py
test/test_kafka_restproxy.py
test/test_single_storage_base.py