Metadata-Version: 2.4
Name: kafi
Version: 0.0.72
Summary: Kafka and Files
Home-page: https://github.com/xdgrulez/kafi
Author: Ralph M. Debusmann
Author-email: matthias.debusmann@gmail.com
License: Apache License 2.0
Classifier: Development Status :: 3 - Alpha
Classifier: Intended Audience :: Developers
Classifier: License :: OSI Approved :: Apache Software License
Classifier: Programming Language :: Python :: 3.10
Classifier: Topic :: Software Development :: Libraries :: Python Modules
License-File: LICENSE
Requires-Dist: confluent-kafka[avro,json,protobuf,schemaregistry]==2.11.1
Requires-Dist: grpcio-tools==1.69.0
Requires-Dist: piny==1.1.0
Requires-Dist: requests==2.32.3
Requires-Dist: azure-storage-blob==12.24.0
Requires-Dist: minio==7.2.14
Requires-Dist: lxml==5.3.0
Requires-Dist: openpyxl==3.1.5
Requires-Dist: pandas==2.2.3
Requires-Dist: pyarrow==18.1.0
Dynamic: author
Dynamic: author-email
Dynamic: classifier
Dynamic: description
Dynamic: description-content-type
Dynamic: home-page
Dynamic: license
Dynamic: license-file
Dynamic: requires-dist
Dynamic: summary
